setup.py
tests/__init__.py
tests/runtests.py
tests/crypto/__init__.py
tests/crypto/tests.py
tests/settings/__init__.py
tests/settings/tests.py
wego/__init__.py
wego/api.py
wego/buttons.py
wego/exceptions.py
wego/settings.py
wego/wechat.py
wego.egg-info/PKG-INFO
wego.egg-info/SOURCES.txt
wego.egg-info/dependency_links.txt
wego.egg-info/requires.txt
wego.egg-info/top_level.txt
wego/helpers/__init__.py
wego/helpers/base_helper.py
wego/helpers/official.py
wego/lib/WEGOBizMsgCrypt.py
wego/lib/__init__.py