Metadata-Version: 1.0
Name: wego
Version: 0.9.4a0
Summary: dead simple wechat sdk
Home-page: https://github.com/wegostudio/wego
Author: Quseit
Author-email: sciooga@gmail.com
License: Apache License
Keywords: wechat sdk
Platform: any
